LICENSE
MANIFEST.in
README.md
main.py
requirements.txt
setup.py
filks/__init__.py
filks/cmudict.py
filks/commands.py
filks/corpus.py
filks/format_selector.py
filks/random2.py
filks/tagged_text.py
filks.egg-info/PKG-INFO
filks.egg-info/SOURCES.txt
filks.egg-info/dependency_links.txt
filks.egg-info/entry_points.txt
filks.egg-info/requires.txt
filks.egg-info/top_level.txt
filks/resources/__init__.py
filks/resources/formats/__init__.py