Metadata-Version: 1.1
Name: filks
Version: 0.1.2
Summary: Generates filks based on a poem format and corpus
Home-page: https://github.com/kcsaff/filks
Author: K.C.Saff
Author-email: kc@saff.net
License: MIT
Platform: UNKNOWN
Classifier: License :: OSI Approved :: MIT License
Classifier: Intended Audience :: Other Audience
Classifier: Programming Language :: Python :: 3
